canvasvg/__init__.py
canvasvg/turtle2img.py
turtle2img/__init__.py
turtle2img/turtle2img.py
turtle2img-1.1.5.dist-info/LICENSE
turtle2img-1.1.5.dist-info/METADATA
turtle2img-1.1.5.dist-info/WHEEL
turtle2img-1.1.5.dist-info/top_level.txt
turtle2img-1.1.5.dist-info/RECORD
