Metadata-Version: 2.1
Name: turtle2img
Version: 1.1.5
Summary: Save turtle images as jpg or png
Home-page: https://github.com/An-20/turtle2img
Author: An-20
License: BSD (3 clauses)
Keywords: turtle,image,png,jpg
Platform: UNKNOWN
Classifier: Development Status :: 5 - Production/Stable
Classifier: License :: OSI Approved :: BSD License
Classifier: Programming Language :: Python
Classifier: Topic :: Software Development :: Libraries
Classifier: Topic :: Software Development :: Libraries :: Python Modules
Classifier: Topic :: Multimedia :: Graphics :: Capture :: Screen Capture
Classifier: Topic :: Multimedia :: Graphics :: Graphics Conversion
License-File: LICENSE
Requires-Dist: svglib
Requires-Dist: reportlab
Requires-Dist: Pillow
